{
  "code": 1,
  "msg": "获取地区",
  "data":[
    {"name": "北京","id":1},
    {"name": "上海","id":2},
    {"name": "天津","id":3},
    {"name": "重庆","id":4},
    {"name": "江苏","id":5},
    {"name": "北京","id":1},
    {"name": "上海","id":2},
    {"name": "天津","id":3},
    {"name": "重庆","id":4},
    {"name": "江苏","id":5},
    {"name": "北京","id":1},
    {"name": "上海","id":2},
    {"name": "天津","id":3},
    {"name": "重庆","id":4},
    {"name": "江苏","id":5},
    {"name": "上海","id":2},
    {"name": "天津","id":3},
    {"name": "重庆","id":4},
    {"name": "江苏","id":5},
    {"name": "北京","id":1},
    {"name": "上海","id":2},
    {"name": "天津","id":3},
    {"name": "重庆","id":4},
    {"name": "江苏","id":5}
  ]
}